{
    "page_29_Name": {
        "/T": "page_29_Name",
        "/FT": "/Tx",
        "/TU": "NAME OF PERSON COMPLETING THIS FORM",
        "/V": "my name"
    },
    "page_29_Title": {
        "/T": "page_29_Title",
        "/FT": "/Tx",
        "/TU": "TITLE",
        "/V": "cqo"
    },
    "page_29_Company": {
        "/T": "page_29_Company",
        "/FT": "/Tx",
        "/TU": "OFFICIAL COMPANY NAME",
        "/V": "sanid"
    },
    "page_29_PrintName": {
        "/T": "page_29_PrintName",
        "/FT": "/Tx",
        "/TU": "Print Name of Owner/Authorized Member",
        "/V": "owner name"
    },
    "page_29_Signature": {
        "/T": "page_29_Signature",
        "/FT": "/Sig",
        "/TU": "Signature of Owner/Authorized Member"
    },
    "page_29_Date": {
        "/T": "page_29_Date",
        "/FT": "/Tx",
        "/TU": "Today\u2019s Date",
        "/V": "date today",
        "/AA": "{'/F': IndirectObject(4124, 0, 2239656085504), '/K': IndirectObject(4123, 0, 2239656085504)}"
    },
    "page_29_ReasonsZero": {
        "/T": "page_29_ReasonsZero",
        "/FT": "/Tx",
        "/Ff": "4096",
        "/V": "page 29 desc"
    }
}